benchmarks/__init__.py
benchmarks/benchmark_concurrent.py
benchmarks/benchmark_kv_cache.py
benchmarks/benchmark_memory.py
benchmarks/benchmark_throughput.py
benchmarks/benchmark_utils.py
benchmarks/run_aiperf_benchmarks.py
benchmarks/run_benchmarks.py
examples/aiperf_metrics.py
examples/audio_example.py
examples/context_validation_example.py
examples/cost_tracking_example.py
examples/debug_streaming.py
examples/dynamo_advanced_demo.py
examples/error_injection_example.py
examples/example_client.py
examples/example_client_sdk.py
examples/example_client_simple.py
examples/example_kv_cache_demo.py
examples/example_load_testing.py
examples/example_moderation_pipeline.py
examples/example_multimodal.py
examples/example_production_workflow.py
examples/example_reasoning_workflow.py
examples/fix_streaming_metrics.py
examples/integration_snippet.py
examples/llm_generation_example.py
examples/metrics_aggregation_demo.py
examples/metrics_streaming_client.py
examples/model_metrics_demo.py
examples/model_registry_demo.py
examples/monitor_metrics.py
examples/multimodal_example.py
examples/rate_limiter_metrics_demo.py
examples/rate_limiting_demo.py
examples/realtime_example.py
examples/run_enhanced_server.py
examples/security_demo.py
examples/semantic_embeddings_example.py
examples/solido_rag_example.py
examples/streaming_client.py
examples/streaming_fix.py
examples/structured_outputs_example.py
examples/test_lora_models.py
examples/test_metrics.py
examples/test_new_config_options.py
examples/test_predicted_outputs.py
examples/test_reasoning_o1.py
examples/test_request_body_streaming.py
examples/test_streaming_metrics.py
examples/test_token_streaming.py
examples/test_usage_billing.py
examples/test_websocket_metrics.py
examples/tool_calling_example.py
examples/vector_store_engine_demo.py
examples/video_example.py
fakeai/__init__.py
fakeai/__main__.py
fakeai/app.py
fakeai/async_server.py
fakeai/audio.py
fakeai/audio_transcriber.py
fakeai/batch_metrics.py
fakeai/cli.py
fakeai-0.3.2.dist-info/licenses/LICENSE
fakeai-0.3.2.dist-info/METADATA
fakeai-0.3.2.dist-info/WHEEL
fakeai-0.3.2.dist-info/entry_points.txt
fakeai-0.3.2.dist-info/top_level.txt
fakeai-0.3.2.dist-info/RECORD
