Metadata-Version: 2.4
Name: fakeai
Version: 0.3.2
Summary: FakeAI: Rapid Development and Testing for AI Infrastructure
Author: Anthony Casagrande
License: Apache-2.0
Project-URL: Homepage, https://github.com/ajcasagrande/fakeai
Project-URL: Bug Tracker, https://github.com/ajcasagrande/fakeai/issues
Project-URL: Documentation, https://github.com/ajcasagrande/fakeai#readme
Project-URL: Source Code, https://github.com/ajcasagrande/fakeai
Classifier: Development Status :: 4 - Beta
Classifier: Intended Audience :: Developers
Classifier: License :: OSI Approved :: Apache Software License
Classifier: Programming Language :: Python :: 3
Classifier: Programming Language :: Python :: 3.10
Classifier: Programming Language :: Python :: 3.11
Classifier: Programming Language :: Python :: 3.12
Classifier: Topic :: Software Development :: Testing
Classifier: Topic :: Software Development :: Libraries :: Python Modules
Requires-Python: >=3.10
License-File: LICENSE
Requires-Dist: fastapi>=0.103.0
Requires-Dist: uvicorn>=0.23.0
Requires-Dist: hypercorn>=0.16.0
Requires-Dist: pydantic>=2.0.0
Requires-Dist: pydantic-settings>=2.0.0
Requires-Dist: numpy>=1.24.0
Requires-Dist: faker>=13.0.0
Requires-Dist: python-multipart>=0.0.9
Requires-Dist: cyclopts>=3.0.0
Requires-Dist: aiohttp>=3.9.0
Provides-Extra: dev
Requires-Dist: pytest>=7.0.0; extra == "dev"
Requires-Dist: pytest-asyncio>=0.21.0; extra == "dev"
Requires-Dist: pytest-cov>=4.0.0; extra == "dev"
Requires-Dist: black>=23.0.0; extra == "dev"
Requires-Dist: isort>=5.12.0; extra == "dev"
Requires-Dist: flake8>=6.0.0; extra == "dev"
Requires-Dist: mypy>=1.0.0; extra == "dev"
Requires-Dist: openai>=1.0.0; extra == "dev"
Requires-Dist: httpx>=0.24.0; extra == "dev"
Provides-Extra: llm
Requires-Dist: tiktoken>=0.5.0; extra == "llm"
Requires-Dist: transformers>=4.30.0; extra == "llm"
Requires-Dist: torch>=2.0.0; extra == "llm"
Provides-Extra: embeddings
Requires-Dist: sentence-transformers>=2.2.0; extra == "embeddings"
Requires-Dist: torch>=2.0.0; extra == "embeddings"
Provides-Extra: vector
Requires-Dist: faiss-cpu>=1.7.4; extra == "vector"
Requires-Dist: numpy>=1.24.0; extra == "vector"
Provides-Extra: all
Requires-Dist: fakeai[dev,embeddings,llm,vector]; extra == "all"
Provides-Extra: publish
Requires-Dist: build>=1.0.0; extra == "publish"
Requires-Dist: twine>=4.0.0; extra == "publish"
Dynamic: license-file
